qoute_Extract/__init__.py
qoute_Extract/favQs_API.py
quote_Extract-0.0.2.dist-info/LICENSE.txt
quote_Extract-0.0.2.dist-info/METADATA
quote_Extract-0.0.2.dist-info/WHEEL
quote_Extract-0.0.2.dist-info/top_level.txt
quote_Extract-0.0.2.dist-info/RECORD
