Metadata-Version: 2.1
Name: quote-Extract
Version: 0.0.2
Summary: Get a variety of Motivational Quotes here
Home-page: UNKNOWN
Author: Ndongmo Christian
Author-email: christainhonore2003@gmail.com
License: MIT
Platform: UNKNOWN
Classifier: Programming Language :: Python :: 3
Classifier: License :: OSI Approved :: MIT License
